stonemark/CHANGES
stonemark/LICENSE
stonemark/__init__.py
stonemark/__main__.py
stonemark/test.py
stonemark-0.3.6.dist-info/METADATA
stonemark-0.3.6.dist-info/WHEEL
stonemark-0.3.6.dist-info/entry_points.txt
stonemark-0.3.6.dist-info/top_level.txt
stonemark-0.3.6.dist-info/RECORD
